proton_mail_trash/__init__.py
proton_mail_trash/golang.py
proton_mail_trash/hydroxide.py
proton_mail_trash/utils.py
proton_mail_trash-1.2.1.dist-info/WHEEL
proton_mail_trash-1.2.1.dist-info/entry_points.txt
proton_mail_trash-1.2.1.dist-info/METADATA
proton_mail_trash-1.2.1.dist-info/RECORD
