Metadata-Version: 2.4
Name: proton-mail-trash
Version: 1.2.1
Summary: Add your description here
Author: GideonBear
License-Expression: GPL-3.0-only
Classifier: License :: OSI Approved :: GNU General Public License v3 (GPLv3)
Classifier: Programming Language :: Python :: 3 :: Only
Classifier: Programming Language :: Python :: 3.13
Requires-Dist: more-itertools>=10.7
Requires-Dist: rich>=14.1
Requires-Python: >=3.13
Project-URL: bugs, https://github.com/GideonBear/proton-mail-trash/issues
Project-URL: homepage, https://github.com/GideonBear/proton-mail-trash
